tests/__init__.py
tests/test_image_utils.py
tests/test_json_utils.py
web_utils_package-0.1.0.dist-info/LICENSE
web_utils_package-0.1.0.dist-info/METADATA
web_utils_package-0.1.0.dist-info/WHEEL
web_utils_package-0.1.0.dist-info/entry_points.txt
web_utils_package-0.1.0.dist-info/top_level.txt
web_utils_package-0.1.0.dist-info/RECORD
