Metadata-Version: 2.1
Name: web-utils-package
Version: 0.1.0
Summary: Python Project package
Author: Wilson Ramirez
Author-email: wil_ramirez02@hotmail.com
License: MIT
License-File: LICENSE
